flask_apiexceptions.py
Flask_ApiExceptions-1.1.2.dist-info/LICENSE.txt
Flask_ApiExceptions-1.1.2.dist-info/METADATA
Flask_ApiExceptions-1.1.2.dist-info/RECORD
Flask_ApiExceptions-1.1.2.dist-info/WHEEL
Flask_ApiExceptions-1.1.2.dist-info/top_level.txt
