Metadata-Version: 2.1
Name: Flask-ApiExceptions
Version: 1.1.2
Summary: Python exceptions serializable to Flask HTTP responses.
Home-page: https://github.com/jperras/Flask-ApiExceptions
Author: Joel Perras
Author-email: joel@nerderati.com
License: MIT
Download-URL: https://github.com/jperras/Flask-ApiExceptions/archive/1.1.2.tar.gz
Keywords: flask,json,exceptions,api
Platform: any
Classifier: Environment :: Web Environment
Classifier: Intended Audience :: Developers
Classifier: Programming Language :: Python
Classifier: Programming Language :: Python :: 2
Classifier: Programming Language :: Python :: 2.7
Classifier: Programming Language :: Python :: 3
Classifier: Programming Language :: Python :: 3.3
Classifier: Programming Language :: Python :: 3.4
Classifier: Programming Language :: Python :: 3.5
Classifier: Programming Language :: Python :: 3.6
Requires-Dist: Flask (>=0.10)
